gordon_janitor/__init__.py
gordon_janitor/exceptions.py
gordon_janitor/interfaces.py
gordon_janitor/main.py
tests/__init__.py
tests/unit/__init__.py
tests/unit/conftest.py
tests/unit/test_main.py
gordon_janitor-0.0.1.dev7.dist-info/LICENSE
gordon_janitor-0.0.1.dev7.dist-info/METADATA
gordon_janitor-0.0.1.dev7.dist-info/WHEEL
gordon_janitor-0.0.1.dev7.dist-info/entry_points.txt
gordon_janitor-0.0.1.dev7.dist-info/top_level.txt
gordon_janitor-0.0.1.dev7.dist-info/RECORD
