Metadata-Version: 2.1
Name: gordon-janitor
Version: 0.0.1.dev7
Summary: DNS record reconciliation for Gordon: Event-driven Cloud DNS
Home-page: https://github.com/spotify/gordon-janitor
Author: Lynn Root
Author-email: lynn@spotify.com
Maintainer: Lynn Root
Maintainer-email: lynn@spotify.com
License: Apache 2.0
Keywords: dns
Platform: UNKNOWN
Classifier: Development Status :: 1 - Planning
Classifier: License :: OSI Approved :: Apache Software License
Classifier: Natural Language :: English
Classifier: Operating System :: POSIX :: Linux
Classifier: Operating System :: MacOS :: MacOS X
Classifier: Programming Language :: Python
Classifier: Programming Language :: Python :: 3
Classifier: Programming Language :: Python :: 3.6
Classifier: Programming Language :: Python :: Implementation :: CPython
Classifier: Topic :: Internet :: Name Service (DNS)
Requires-Dist: click
Requires-Dist: gordon-dns
Requires-Dist: setuptools
Requires-Dist: toml
Requires-Dist: ulogger
Requires-Dist: zope.interface
